mypy_extras/__init__.py
mypy_extras/attr_of.py
mypy_extras/plugin/__init__.py
mypy_extras/plugin/entrypoint.py
mypy_extras/plugin/features/__init__.py
mypy_extras/plugin/features/attr_of.py
mypy_extras/plugin/features/ensure_attr.py
mypy_extras/plugin/typeops/__init__.py
mypy_extras/plugin/typeops/definitions.py
mypy_extras/plugin/typeops/fallbacks.py
mypy_extras/py.typed
mypy_extras-0.1.0.dist-info/LICENSE
mypy_extras-0.1.0.dist-info/WHEEL
mypy_extras-0.1.0.dist-info/METADATA
mypy_extras-0.1.0.dist-info/RECORD
