Metadata-Version: 2.1
Name: mypy-extras
Version: 0.1.0
Summary: A collection of extra types and features for mypy
Home-page: https://github.com/wemake.services/mypy-extras
License: MIT
Requires-Python: >=3.6,<3.9
Classifier: Development Status :: 3 - Alpha
Classifier: Intended Audience :: Developers
Classifier: License :: OSI Approved :: MIT License
Classifier: Operating System :: OS Independent
Classifier: Programming Language :: Python :: 3
Classifier: Programming Language :: Python :: 3.6
Classifier: Programming Language :: Python :: 3.7
Classifier: Programming Language :: Python :: 3.8
Classifier: Topic :: Software Development :: Libraries :: Python Modules
Project-URL: Repository, https://github.com/wemake.services/mypy-extras
